botcity_aux/__init__.py
botcity_aux/bot_runner.py
botcity_aux/logger_config.py
botcity_aux/telegram_plugin.py
botcity_rpa-0.1.0.dist-info/LICENSE
botcity_rpa-0.1.0.dist-info/METADATA
botcity_rpa-0.1.0.dist-info/WHEEL
botcity_rpa-0.1.0.dist-info/entry_points.txt
botcity_rpa-0.1.0.dist-info/top_level.txt
botcity_rpa-0.1.0.dist-info/RECORD
